setup.py
civeng/__init__.py
civeng/civeng_unittest.py
civeng/dict_.py
civeng/funcs.py
civeng/mathml2.py
civeng/results.py
civeng.egg-info/PKG-INFO
civeng.egg-info/SOURCES.txt
civeng.egg-info/dependency_links.txt
civeng.egg-info/not-zip-safe
civeng.egg-info/top_level.txt
civeng/concrete/__init__.py
civeng/concrete/cat262.py
civeng/concrete/params.py
civeng/concrete/modules/__init__.py
civeng/concrete/modules/bending_force.py
civeng/concrete/modules/shear_force.py
civeng/steel/cat263.py
civeng/steel/cat263_unittest.py
civeng/steel/params.py
civeng/steel/props.py
civeng/steel/props_unittest.py
civeng/steel/stats.py
civeng/steel/szs.db
civeng/steel/szs.py
civeng/steel/modules/amazius.py