Metadata-Version: 1.0
Name: civeng
Version: 0.3.0
Summary: civil engineering tools
Home-page: https://pypi.python.org/pypi/civeng
Author: dutu8ure
Author-email: dutu8ure@gmail.com
License: GPLv3
Platform: UNKNOWN
